cog_to_zarr/__init__.py
cog_to_zarr/cli.py
cog_to_zarr/cog_to_zarr.py
cog_to_zarr/types.py
cog_to_zarr-0.1.0.dist-info/LICENSE
cog_to_zarr-0.1.0.dist-info/METADATA
cog_to_zarr-0.1.0.dist-info/WHEEL
cog_to_zarr-0.1.0.dist-info/entry_points.txt
cog_to_zarr-0.1.0.dist-info/RECORD
