Metadata-Version: 2.3
Name: cog_to_zarr
Version: 0.1.0
Summary: 
Author: Jeff Albrecht
Author-email: geospatialjeff@gmail.com
Requires-Python: >=3.11,<4
Classifier: Programming Language :: Python :: 3
Classifier: Programming Language :: Python :: 3.11
Classifier: Programming Language :: Python :: 3.12
Classifier: Programming Language :: Python :: 3.13
Requires-Dist: async-tiff (==0.1.0)
Requires-Dist: click (>=8.2.1,<9.0.0)
Requires-Dist: dask (>=2025.5.1,<2026.0.0)
Requires-Dist: geojson-pydantic (>=2.0.0,<3.0.0)
Requires-Dist: pydantic (>=2.11.7,<3.0.0)
Requires-Dist: pystac (>=1.13.0,<2.0.0)
Requires-Dist: pystac-client (>=0.8.6,<0.9.0)
Requires-Dist: rioxarray (>=0.19.0,<0.20.0)
Requires-Dist: xarray (>=2025.6.1,<2026.0.0)
